Metadata-Version: 1.0
Name: proapisgp
Version: 1.0.0
Summary: ProAPIs Google Play API.
Home-page: https://proapis.cloud
Author: ProAPIs
Author-email: sales@proapis.cloud
License: GPL3
Platform: UNKNOWN
